offlam/Configuration.py
offlam/__init__.py
offlam/algorithm.py
offlam/Util/PddlParser.py
offlam/Util/__init__.py
offlam/Util/generate_dataframe.py
offlam/Util/metrics.py
offlam/Util/plot_results.py
offlam/Util/util.py
offlam/src/Action.py
offlam/src/ActionModel.py
offlam/src/Learner.py
offlam/src/Observation.py
offlam/src/Operator.py
offlam/src/Trace.py
offlam/src/__init__.py
offlam-1.0.0.dist-info/METADATA
offlam-1.0.0.dist-info/WHEEL
offlam-1.0.0.dist-info/top_level.txt
offlam-1.0.0.dist-info/RECORD
