Metadata-Version: 2.4
Name: offlam
Version: 1.0.0
Summary: Action Model Learning from Noisy Traces: a Probabilistic Approach.
Author-email: Leonardo Lamanna <llamanna@fbk.eu>
Maintainer-email: Leonardo Lamanna <llamanna@fbk.eu>
License-Expression: MIT
Project-URL: Homepage, https://github.com/LamannaLeonardo/OffLAM
Project-URL: Documentation, https://github.com/LamannaLeonardo/OffLAM
Project-URL: Repository, https://github.com/LamannaLeonardo/OffLAM
Project-URL: Bug Tracker, https://github.com/LamannaLeonardo/OffLAM/issues
Keywords: action model learning,domain model learning,action model acquisition
Classifier: Intended Audience :: Science/Research
Classifier: Programming Language :: Python
Classifier: Topic :: Scientific/Engineering :: Artificial Intelligence
Requires-Python: >=3.8
Requires-Dist: numpy
Requires-Dist: pandas
Requires-Dist: matplotlib
Requires-Dist: openpyxl
